IDINSDK/__init__.py
IDINSDK-0.0.2.dist-info/METADATA
IDINSDK-0.0.2.dist-info/WHEEL
IDINSDK-0.0.2.dist-info/top_level.txt
IDINSDK-0.0.2.dist-info/RECORD
