Metadata-Version: 2.1
Name: IDINSDK
Version: 0.0.2
Summary: Python SDK for IDIN Blockchain API
Home-page: https://git.finema.co/finema/idinsdk-python
Author: Finema Co., Ltd.
Author-email: hi@finema.co
License: UNKNOWN
Platform: UNKNOWN
Classifier: Programming Language :: Python :: 3
Classifier: Operating System :: OS Independent
Requires-Python: >=3.6
